Compiled from "Hello.java"
public class Hello {
  public Hello();
    Code:
       0: aload_0
       1: invokespecial #1                  // Method java/lang/Object."<init>":()V
       4: return

  public static void main(java.lang.String[]);
    Code:
       0: getstatic     #2                  // Field java/lang/System.out:Ljava/io/PrintStream;
       3: ldc           #3                  // String HelloWord
       5: iconst_0
       6: anewarray     #4                  // class java/lang/Object
       9: invokevirtual #5                  // Method java/io/PrintStream.printf:(Ljava/lang/String;[Ljava/lang/Object;)Ljava/io/PrintStream;
      12: pop
      13: return
}
